<?xml version="1.0" encoding="UTF-8"?>
<typeSystemDescription xmlns="http://uima.apache.org/resourceSpecifier">

    <name>TypeSystemOffensiveSpeech</name>

    <description>
        Types for processing offensive speech with different types, abusive, discriminatory, etc.
    </description>

    <version>1.0</version>

    <vendor/>

    <imports>

        <import name="desc.type.TextTechnologyAnnotation"/>

        <import name="desc.type.TypeSystemModelMeta"/>


    </imports>
    <types>
        <typeDescription>
            <name>org.texttechnologylab.annotation.OffensiveSpeech</name>
            <description>
                Offensive speech output, not only offensive or not offensive, but also the type of offensive speech
            </description>
            <supertypeName>uima.tcas.Annotation</supertypeName>
            <features>

                <featureDescription>

                    <name>Offensives</name>

                    <description>Set of offensive types with key and Value</description>

                    <rangeTypeName>uima.cas.FSArray</rangeTypeName>

                    <elementType>org.texttechnologylab.annotation.AnnotationComment</elementType>

                </featureDescription>

                <featureDescription>

                    <name>model</name>

                    <description>The model which, was used for the classification</description>

                    <rangeTypeName>org.texttechnologylab.annotation.model.MetaData</rangeTypeName>

                </featureDescription>
            </features>
        </typeDescription>
    </types>
</typeSystemDescription>
